simple_calculator/__init__.py
simple_calculator/calculator.py
yc_calculator-0.1.0.dist-info/licenses/LICENSE
yc_calculator-0.1.0.dist-info/METADATA
yc_calculator-0.1.0.dist-info/WHEEL
yc_calculator-0.1.0.dist-info/top_level.txt
yc_calculator-0.1.0.dist-info/RECORD
